arcor2_logger/VERSION
arcor2_logger/__init__.py
arcor2_logger/py.typed
arcor2_logger/object_types/__init__.py
arcor2_logger/object_types/logging_mixin.py
arcor2_logger/scripts/__init__.py
arcor2_logger/scripts/logger.py
arcor2_logger-0.2.0.dist-info/METADATA
arcor2_logger-0.2.0.dist-info/WHEEL
arcor2_logger-0.2.0.dist-info/entry_points.txt
arcor2_logger-0.2.0.dist-info/namespace_packages.txt
arcor2_logger-0.2.0.dist-info/top_level.txt
arcor2_logger-0.2.0.dist-info/RECORD
