Metadata-Version: 2.1
Name: arcor2-logger
Version: 0.2.0
Summary: ARCOR2 Logger service.
Author: Robo@FIT
Author-email: imaterna@fit.vut.cz
License: LGPL
Classifier: Development Status :: 3 - Alpha
Classifier: Intended Audience :: Developers
Classifier: Topic :: Software Development :: Build Tools
Classifier: License :: OSI Approved :: GNU Lesser General Public License v3 (LGPLv3)
Classifier: Programming Language :: Python :: 3.11
Classifier: Natural Language :: English
Classifier: Topic :: Scientific/Engineering
Requires-Python: ==3.11.*
Requires-Dist: aiologger (~=0.7.0)
Requires-Dist: aiorun (~=2023.7.2)
Requires-Dist: arcor2 (~=1.3.0)
Requires-Dist: dataclasses-jsonschema[apispec,fast-dateparsing,fast-validation] (~=2.16.0)
Requires-Dist: websocket-client (~=1.7.0)
Requires-Dist: websockets (~=12.0)
